assignment1/full_adder cs220/full_adder cs220/half_adder.v
module half_adder(a,b,sum, carry);
input a,b;
output sum,carry;
xor(sum,a,b);
and(carry,a,b);
endmodule

assignment1/full_adder cs220/full_adder cs220/full_adder.v
`include "half_adder.v"
module full_adder(a,b,cin,cout,sum);
input a,b,cin;
output cout,sum;
wire s_1,cout_1,cout_2;
half_adder hlf1(a,b,s_1,cout_1);
half_adder hlf2(cin,s_1,sum,cout_2);
or o1(cout,cout_2,cout_1);
endmodule

assignment1/full_adder cs220/full_adder cs220/full_adder_tb.v
`include "full_adder.v"
module full_adder_tb;
reg a,b,cin;
wire cout, sum;
full_adder uut(.a(a),.b(b),.cin(cin),.cout(cout),.sum(sum));
initial begin
    $dumpfile("full_tb.vcd");
    $dumpvars(0,full_adder_tb);
end

initial begin a=1'b1;  #4; a=1'b0;#10 $stop();end
initial begin b=1'b1; forever #2 b=~b;end
initial begin cin=1'b1;forever #1 cin=~cin; #10 $stop();end
initial begin $monitor(" time=%0d A=%b B=%b Cin=%b Sum=%b Cout=%b",$time,a,b,cin,sum,cout);end
endmodule

assignment1/full_adder cs220/full_adder cs220/full_tb.vcd
$date
	Sat Jan 14 14:31:43 2023
$end
$version
	Icarus Verilog
$end
$timescale
	1s
$end
$scope module full_adder_tb $end
$var wire 1 ! sum $end
$var wire 1 " cout $end
$var reg 1 # a $end
$var reg 1 $ b $end
$var reg 1 % cin $end
$scope module uut $end
$var wire 1 # a $end
$var wire 1 $ b $end
$var wire 1 % cin $end
$var wire 1 " cout $end
$var wire 1 ! sum $end
$var wire 1 & s_1 $end
$var wire 1 ' cout_2 $end
$var wire 1 ( cout_1 $end
$scope module hlf1 $end
$var wire 1 # a $end
$var wire 1 $ b $end
$var wire 1 ( carry $end
$var wire 1 & sum $end
$upscope $end
$scope module hlf2 $end
$var wire 1 % a $end
$var wire 1 & b $end
$var wire 1 ' carry $end
$var wire 1 ! sum $end
$upscope $end
$upscope $end
$upscope $end
$enddefinitions $end
#0
$dumpvars
1(
0'
0&
1%
1$
1#
1"
1!
$end
#1
0!
0%
#2
1'
1&
0(
1%
0$
#3
0"
1!
0'
0%
#4
1"
0!
1'
1%
1$
0#
#5
0"
1!
0'
0%
#6
0&
1%
0$
#7
0!
0%
#8
1"
1'
1&
1%
1$
#9
0"
1!
0'
0%
#10
0&
1%
0$
#11
0!
0%
#12
1"
1'
1&
1%
1$
#13
0"
1!
0'
0%
