assignment1/multiplexer4to1/multiplexer4to1/multiplexer4to1.v
module multiplexer4to1(sel,I0,I1,I2,I3,out);
input [1:0]sel;
input [31:0]I0;
input [31:0]I1;
input [31:0]I2;
input [31:0]I3;
output reg [31:0]out;
always@(I0 or I1 or I2 or I3 or sel)begin
    case (sel)
    2'b00 : out=I0;
    2'b01 : out=I1;
    2'b10 : out=I2;
    2'b11 : out=I3;
    default: out =0;
    endcase
end
endmodule

assignment1/multiplexer4to1/multiplexer4to1/multiplexer4to1_tb.v
`include "multiplexer4to1.v"
module multiplexer4to1_tb;
reg [31:0] I0,I1,I2,I3;
reg [1:0]sel;
wire [31:0]out;
multiplexer4to1 uut(.sel(sel),.I0(I0),.I1(I1),.I2(I2),.I3(I3),.out(out));
integer i;
initial begin
    $monitor("time = %0t sel=0x%0h I0=0x%0h I1=0x%0h I2=0x%0h I3=0x%0h out=0x%0h", $time,sel,I0,I1,I2,I3,out);
end
initial begin
    $dumpfile("multi_4to1.vcd");
    $dumpvars(0,multiplexer4to1_tb);
end
initial begin
sel<=0;
I0 <= $random;
I1 <= $random;
I2 <= $random; 
I3 <= $random;
forever #5 sel=sel+1;
end
initial begin
    #40 $finish;
end

endmodule

assignment1/multiplexer4to1/multiplexer4to1/multi_4to1.vcd
$date
	Sun Jan 15 11:56:56 2023
$end
$version
	Icarus Verilog
$end
$timescale
	1s
$end
$scope module multiplexer4to1_tb $end
$var wire 32 ! out [31:0] $end
$var reg 32 " I0 [31:0] $end
$var reg 32 # I1 [31:0] $end
$var reg 32 $ I2 [31:0] $end
$var reg 32 % I3 [31:0] $end
$var reg 2 & sel [1:0] $end
$scope module uut $end
$var wire 32 ' I0 [31:0] $end
$var wire 32 ( I1 [31:0] $end
$var wire 32 ) I2 [31:0] $end
$var wire 32 * I3 [31:0] $end
$var wire 2 + sel [1:0] $end
$var reg 32 , out [31:0] $end
$upscope $end
$upscope $end
$enddefinitions $end
#0
$dumpvars
b10010000101010011010100100100 ,
b0 +
b10110001111100000101011001100011 *
b10000100100001001101011000001001 )
b11000000100010010101111010000001 (
b10010000101010011010100100100 '
b0 &
b10110001111100000101011001100011 %
b10000100100001001101011000001001 $
b11000000100010010101111010000001 #
b10010000101010011010100100100 "
b10010000101010011010100100100 !
$end
#5
b11000000100010010101111010000001 !
b11000000100010010101111010000001 ,
b1 &
b1 +
#10
b10000100100001001101011000001001 !
b10000100100001001101011000001001 ,
b10 &
b10 +
#15
b10110001111100000101011001100011 !
b10110001111100000101011001100011 ,
b11 &
b11 +
#20
b10010000101010011010100100100 !
b10010000101010011010100100100 ,
b0 &
b0 +
#25
b11000000100010010101111010000001 !
b11000000100010010101111010000001 ,
b1 &
b1 +
#30
b10000100100001001101011000001001 !
b10000100100001001101011000001001 ,
b10 &
b10 +
#35
b10110001111100000101011001100011 !
b10110001111100000101011001100011 ,
b11 &
b11 +
#40
b10010000101010011010100100100 !
b10010000101010011010100100100 ,
b0 &
b0 +
