assignment1/opcode decoder/opcode decoder/decoder.v
module decoder(in,out,en);
input [2:0] in;
output reg [7:0] out;
input en;
always@(in or en) begin
    if(en) begin out=8'd0;
          case (in)
              3'b000: out[0]=1'b1;
              3'b001: out[1]=1'b1;
              3'b010: out[2]=1'b1;
              3'b011: out[3]=1'b1;
              3'b100: out[4]=1'b1;
              3'b101: out[5]=1'b1;
              3'b110: out[6]=1'b1;
              3'b111: out[7]=1'b1;
              default: out=8'd0;
          endcase
    end
else out =8'd0;
end
endmodule

assignment1/opcode decoder/opcode decoder/decoder_tb.v
`include "decoder.v"
module decoder_tb;
wire [7:0] out;
reg en;
reg [2:0] in;
integer i;

decoder uut(in,out,en);
initial begin
    $dumpfile("decoder.vcd");
    $dumpvars(0,decoder_tb);
end
initial begin  
 $monitor( "en=%b, in=%d, out=%b ", en, in, out);
end
initial begin
    for ( i=0; i<16; i=i+1) 
        begin
           {en,in}  = i;
            #1;
        end
end
endmodule

assignment1/opcode decoder/opcode decoder/decoder.vcd
$date
	Sat Jan 14 18:52:46 2023
$end
$version
	Icarus Verilog
$end
$timescale
	1s
$end
$scope module decoder_tb $end
$var wire 8 ! out [7:0] $end
$var reg 1 " en $end
$var reg 3 # in [2:0] $end
$var integer 32 $ i [31:0] $end
$scope module uut $end
$var wire 1 " en $end
$var wire 3 % in [2:0] $end
$var reg 8 & out [7:0] $end
$upscope $end
$upscope $end
$enddefinitions $end
#0
$dumpvars
b0 &
b0 %
b0 $
b0 #
0"
b0 !
$end
#1
b1 #
b1 %
b1 $
#2
b10 #
b10 %
b10 $
#3
b11 #
b11 %
b11 $
#4
b100 #
b100 %
b100 $
#5
b101 #
b101 %
b101 $
#6
b110 #
b110 %
b110 $
#7
b111 #
b111 %
b111 $
#8
b1 !
b1 &
1"
b0 #
b0 %
b1000 $
#9
b10 !
b10 &
b1 #
b1 %
b1001 $
#10
b100 !
b100 &
b10 #
b10 %
b1010 $
#11
b1000 !
b1000 &
b11 #
b11 %
b1011 $
#12
b10000 !
b10000 &
b100 #
b100 %
b1100 $
#13
b100000 !
b100000 &
b101 #
b101 %
b1101 $
#14
b1000000 !
b1000000 &
b110 #
b110 %
b1110 $
#15
b10000000 !
b10000000 &
b111 #
b111 %
b1111 $
#16
b10000 $
