assignment1/full subtracter cs220/full subtracter cs220/half_subtract.v
module half_subtract(a,b,diff,carry);
input a,b;
output diff,carry;
wire an;
not(an,a);
xor(diff,a,b);
and(carry,an,b);
endmodule

assignment1/full_subtract_32/full_subtract_32/full_subtract.v
`include "half_subtract.v"
module full_subtract(a,b,bin,d,bout);
input a,b,bin;
output d,bout;
wire dif1,carry1,carry2;
half_subtract hf1(a,b,dif1,carry1);
half_subtract hf2(dif1,bin,d,carry2);
or o1(bout,carry1,carry2);
endmodule

assignment1/full subtracter cs220/full subtracter cs220/full_subtract_tb.v
`include "full_subtract.v"
module full_subtract_tb;
reg a,b,bin;
wire d, bout;
full_subtract uut(.a(a),.b(b),.bin(bin),.d(d),.bout(bout));
// inputs are reg and outputs are wire
initial begin 
    $dumpfile("full_subtract.vcd");
    $dumpvars(0,full_subtract_tb);
end
initial begin a=1'b1;  #4; a=1'b0;#10 $stop();end
initial begin b=1'b1; forever #2 b=~b;end
initial begin bin=1'b1;forever #1 bin=~bin; #10 $finish();end
initial begin $monitor(" time=%0d A=%b B=%b bin=%b Sum=%b bout=%b",$time,a,b,bin,d,bout);end
endmodule

assignment1/full subtracter cs220/full subtracter cs220/full_subtract.vcd
$date
	Sat Jan 14 14:36:31 2023
$end
$version
	Icarus Verilog
$end
$timescale
	1s
$end
$scope module full_subtract_tb $end
$var wire 1 ! d $end
$var wire 1 " bout $end
$var reg 1 # a $end
$var reg 1 $ b $end
$var reg 1 % bin $end
$scope module uut $end
$var wire 1 # a $end
$var wire 1 $ b $end
$var wire 1 % bin $end
$var wire 1 " bout $end
$var wire 1 & dif1 $end
$var wire 1 ! d $end
$var wire 1 ' carry2 $end
$var wire 1 ( carry1 $end
$scope module hf1 $end
$var wire 1 # a $end
$var wire 1 ) an $end
$var wire 1 $ b $end
$var wire 1 ( carry $end
$var wire 1 & diff $end
$upscope $end
$scope module hf2 $end
$var wire 1 & a $end
$var wire 1 * an $end
$var wire 1 % b $end
$var wire 1 ' carry $end
$var wire 1 ! diff $end
$upscope $end
$upscope $end
$upscope $end
$enddefinitions $end
#0
$dumpvars
1*
0)
0(
1'
0&
1%
1$
1#
1"
1!
$end
#1
0"
0!
0'
0%
#2
0"
0*
0'
1&
1%
0$
#3
1!
0%
#4
1"
0!
1(
1)
1%
1$
0#
#5
1!
0%
#6
1'
1*
1"
0&
0(
1%
0$
#7
0"
0!
0'
0%
#8
0*
1"
0'
1&
1(
1%
1$
#9
1!
0%
#10
1'
1*
1"
0&
0(
1%
0$
#11
0"
0!
0'
0%
#12
0*
1"
0'
1&
1(
1%
1$
#13
1!
0%
